{"response":{"legislator":[{"@attributes":{"cid":"N00036154","firstlast":"Don Norcross","lastname":"NORCROSS","party":"D","office":"NJ01","gender":"M","first_elected":"2014","exit_code":"0","comments":"","phone":"202-225-6501","fax":"202-225-6583","website":"https://norcross.house.gov","webform":"http://norcross.house.gov/contact","congress_office":"1531 Longworth House Office Building","bioguide_id":"N000188","votesmart_id":"","feccandid":"H4NJ01084","twitter_id":"DonaldNorcross","youtube_url":"","facebook_id":"DonaldNorcrossNJ","birthdate":"1958-12-13"}},{"@attributes":{"cid":"N00000851","firstlast":"Frank LoBiondo","lastname":"LOBIONDO","party":"R","office":"NJ02","gender":"M","first_elected":"1994","exit_code":"4","comments":"Retiring at end of 115th","phone":"202-225-6572","fax":"202-225-3318","website":"http://lobiondo.house.gov","webform":"https://lobiondo.house.gov/contact-me/email-me","congress_office":"2427 Rayburn House Office Building","bioguide_id":"L000554","votesmart_id":"21890","feccandid":"H2NJ02037","twitter_id":"RepLoBiondo","youtube_url":"https://youtube.com/USRepFrankLoBiondo","facebook_id":"FrankLoBiondo","birthdate":"1946-05-12"}},{"@attributes":{"cid":"N00036155","firstlast":"Thomas MacArthur","lastname":"MACARTHUR","party":"R","office":"NJ03","gender":"M","first_elected":"2014","exit_code":"21","comments":"Lost general election","phone":"202-225-4765","fax":"202-225-0778","website":"https://macarthur.house.gov","webform":"","congress_office":"506 Cannon House Office Building","bioguide_id":"M001193","votesmart_id":"","feccandid":"H4NJ03130","twitter_id":"RepTomMacArthur","youtube_url":"","facebook_id":"CongressmanTomMacArthur","birthdate":"1960-10-16"}},{"@attributes":{"cid":"N00009816","firstlast":"Chris Smith","lastname":"SMITH","party":"R","office":"NJ04","gender":"M","first_elected":"1980","exit_code":"0","comments":"","phone":"202-225-3765","fax":"202-225-7768","website":"http://chrissmith.house.gov","webform":"https://chrissmith.house.gov/contact/write.htm","congress_office":"2373 Rayburn House Office Building","bioguide_id":"S000522","votesmart_id":"26952","feccandid":"H8NJ04014","twitter_id":"RepChrisSmith","youtube_url":"https://youtube.com/USRepChrisSmith","facebook_id":"RepChrisSmith","birthdate":"1953-03-04"}},{"@attributes":{"cid":"N00036944","firstlast":"Josh Gottheimer","lastname":"GOTTHEIMER","party":"D","office":"NJ05","gender":"M","first_elected":"2016","exit_code":"0","comments":"","phone":"202-225-4465","fax":"","website":"https://gottheimer.house.gov","webform":"","congress_office":"213 Cannon House Office Building","bioguide_id":"G000583","votesmart_id":"","feccandid":"","twitter_id":"RepJoshG","youtube_url":"","facebook_id":"RepJoshG","birthdate":"1975-03-08"}},{"@attributes":{"cid":"N00000781","firstlast":"Frank Pallone Jr.","lastname":"PALLONE","party":"D","office":"NJ06","gender":"M","first_elected":"1988","exit_code":"0","comments":"","phone":"202-225-4671","fax":"202-225-9665","website":"https://pallone.house.gov","webform":"https://pallone.house.gov/contact-me/email-me","congress_office":"237 Cannon House Office Building","bioguide_id":"P000034","votesmart_id":"26951","feccandid":"H8NJ03073","twitter_id":"FrankPallone","youtube_url":"https://youtube.com/repfrankpallone","facebook_id":"repfrankpallone","birthdate":"1951-10-30"}},{"@attributes":{"cid":"N00000898","firstlast":"Leonard Lance","lastname":"LANCE","party":"R","office":"NJ07","gender":"M","first_elected":"2008","exit_code":"21","comments":"Lost general election","phone":"202-225-5361","fax":"202-225-9460","website":"http://lance.house.gov","webform":"https://lance.house.gov/contact-me1","congress_office":"2352 Rayburn House Office Building","bioguide_id":"L000567","votesmart_id":"4443","feccandid":"H6NJ12136","twitter_id":"RepLanceNJ7","youtube_url":"https://youtube.com/CongressmanLance","facebook_id":"CongressmanLance","birthdate":"1952-06-25"}},{"@attributes":{"cid":"N00027523","firstlast":"Albio Sires","lastname":"SIRES","party":"D","office":"NJ08","gender":"M","first_elected":"2006","exit_code":"0","comments":"","phone":"202-225-7919","fax":"202-226-0792","website":"https://sires.house.gov","webform":"https://sires.house.gov/contact-me/email-me","congress_office":"2342 Rayburn House Office Building","bioguide_id":"S001165","votesmart_id":"22510","feccandid":"H6NJ13191","twitter_id":"RepSires","youtube_url":"https://youtube.com/RepSiresNJ13","facebook_id":"RepAlbioSires","birthdate":"1951-01-26"}},{"@attributes":{"cid":"N00000751","firstlast":"Bill Pascrell Jr.","lastname":"PASCRELL","party":"D","office":"NJ09","gender":"M","first_elected":"1996","exit_code":"0","comments":"","phone":"202-225-5751","fax":"202-225-5782","website":"http://pascrell.house.gov","webform":"https://pascrell.house.gov/contact/email-me","congress_office":"2370 Rayburn House Office Building","bioguide_id":"P000096","votesmart_id":"478","feccandid":"H6NJ08118","twitter_id":"BillPascrell","youtube_url":"https://youtube.com/RepPascrell","facebook_id":"pascrell","birthdate":"1937-01-25"}},{"@attributes":{"cid":"N00034639","firstlast":"Donald M Payne Jr.","lastname":"PAYNE","party":"D","office":"NJ10","gender":"M","first_elected":"2012","exit_code":"0","comments":"","phone":"202-225-3436","fax":"202-225-4160","website":"http://payne.house.gov","webform":"http://payne.house.gov/contact/email-me","congress_office":"132 Cannon House Office Building","bioguide_id":"P000604","votesmart_id":"90668","feccandid":"H2NJ10154","twitter_id":"RepDonaldPayne","youtube_url":"","facebook_id":"DonaldPayneJr","birthdate":"1958-12-17"}},{"@attributes":{"cid":"N00000684","firstlast":"Rodney Frelinghuysen","lastname":"FRELINGHUYSEN","party":"R","office":"NJ11","gender":"M","first_elected":"1994","exit_code":"4","comments":"Retiring at end of 115th","phone":"202-225-5034","fax":"202-225-3186","website":"https://frelinghuysen.house.gov","webform":"https://frelinghuysenforms.house.gov/contact-form","congress_office":"2306 Rayburn House Office Building","bioguide_id":"F000372","votesmart_id":"22177","feccandid":"H2NJ05014","twitter_id":"USRepRodney","youtube_url":"https://youtube.com/RepFrelinghuysen","facebook_id":"rfrelinghuysen","birthdate":"1946-04-29"}},{"@attributes":{"cid":"N00036158","firstlast":"Bonnie Coleman","lastname":"COLEMAN","party":"D","office":"NJ12","gender":"F","first_elected":"2014","exit_code":"0","comments":"","phone":"202-225-5801","fax":"202-225-6025","website":"https://watsoncoleman.house.gov","webform":"","congress_office":"1535 Longworth House Office Building","bioguide_id":"W000822","votesmart_id":"","feccandid":"H4NJ12149","twitter_id":"RepBonnie","youtube_url":"","facebook_id":"RepBonnie","birthdate":"1945-02-06"}},{"@attributes":{"cid":"N00000699","firstlast":"Robert Menendez","lastname":"MENENDEZ","party":"D","office":"NJS1","gender":"M","first_elected":"2006","exit_code":"0","comments":"","phone":"202-224-4744","fax":"202-228-2197","website":"https://www.menendez.senate.gov","webform":"https://www.menendez.senate.gov/contact","congress_office":"528 Hart Senate Office Building","bioguide_id":"M000639","votesmart_id":"26961","feccandid":"H2NJ13075","twitter_id":"SenatorMenendez","youtube_url":"https://youtube.com/SenatorMenendezNJ","facebook_id":"senatormenendez","birthdate":"1954-01-01"}},{"@attributes":{"cid":"N00035267","firstlast":"Cory Booker","lastname":"BOOKER","party":"D","office":"NJS2","gender":"M","first_elected":"2013","exit_code":"0","comments":"","phone":"202-224-3224","fax":"202-224-8378","website":"https://www.booker.senate.gov","webform":"https://www.booker.senate.gov/?p=contact","congress_office":"359 Dirksen Senate Office Building","bioguide_id":"B001288","votesmart_id":"76151","feccandid":"S4NJ00185","twitter_id":"CoryBooker","youtube_url":"https://youtube.com/SenCoryBooker","facebook_id":"corybooker","birthdate":"1969-04-27"}}]}}
